{
    "id": "org.kde.klettres",
    "runtime": "org.kde.Platform",
    "runtime-version": "5.15",
    "sdk": "org.kde.Sdk",
    "command": "klettres",
    "rename-icon": "klettres",
    "finish-args": [
        "--share=network", 
        "--share=ipc", 
        "--socket=x11", 
        "--socket=wayland",
        "--device=dri",
        "--socket=pulseaudio"
    ],

    "modules": [
        {
            "name": "klettres",
            "buildsystem": "cmake-ninja",
            "sources": [ 
                { 
                   "type": "archive", 
                   "url": "https://download.kde.org/stable/release-service/20.12.0/src/klettres-20.12.0.tar.xz",
                   "sha256": "cdb85764f5f28c9f03abad20329206d5bf5a5c1481a8b9f550ef5502160f5ffa"
                },
                {
                    "type": "patch",
                    "path": "appdata.patch"
                }                 
            ]
        }
    ]
}
